pyomegle/__init__.py
pyomegle/pyomegle.py
pyomegle-1.7.dist-info/LICENSE
pyomegle-1.7.dist-info/METADATA
pyomegle-1.7.dist-info/WHEEL
pyomegle-1.7.dist-info/top_level.txt
pyomegle-1.7.dist-info/RECORD
