Metadata-Version: 2.1
Name: pyomegle
Version: 1.7
Summary: Python API for Omegle webchat
Home-page: https://github.com/elias94/pyomegle
Author: Elia Scotto
Author-email: eliascotto94@gmail.com
License: MIT
Platform: UNKNOWN
Classifier: Development Status :: 5 - Production/Stable
Classifier: License :: OSI Approved :: MIT License
Classifier: Operating System :: POSIX
Classifier: Topic :: Communications :: Chat
Classifier: Programming Language :: Python
Classifier: Programming Language :: Python :: 3
Classifier: Programming Language :: Python :: 3.7
Classifier: Topic :: Internet :: WWW/HTTP :: Browsers
Requires-Dist: mechanize
